assignment_5/4_bitcounter_reset.v
module counter_4bit_sync(
input clk,
input reset,
output reg [3:0] count);
always@(posedge clk) begin
if(reset)
count<=4'b0000;
else
count<=count+1;
end
endmodule

assignment_5/4_bitcounter_reset_tb.v
module tb_counter_4bit_sync;
reg clk;
reg reset;
wire [3:0] count;
counter_4bit_sync uut(.clk(clk),.reset(reset),.count(count));
initial clk=0;
always #5 clk=~clk;
initial begin 
	 
$monitor ("time=%0t clk=%b reset=%b count=%b" , $time , clk , reset , count );

$dumpfile("counter_4bit_sync.vcd");

$dumpvars(0,tb_counter_4bit_sync);
reset=1;
#10;
reset=0;
#100;
reset=1;
#10;
reset=0;
#50;
$finish;
end
endmodule

assignment_5/counter_4bit_sync.vcd
$date
	Sat Sep 13 12:56:33 2025
$end
$version
	Icarus Verilog
$end
$timescale
	1s
$end
$scope module tb_counter_4bit_sync $end
$var wire 4 ! count [3:0] $end
$var reg 1 " clk $end
$var reg 1 # reset $end
$scope module uut $end
$var wire 1 " clk $end
$var wire 1 # reset $end
$var reg 4 $ count [3:0] $end
$upscope $end
$upscope $end
$enddefinitions $end
$comment Show the parameter values. $end
$dumpall
$end
#0
$dumpvars
bx $
1#
0"
bx !
$end
#5
b0 !
b0 $
1"
#10
0"
0#
#15
b1 !
b1 $
1"
#20
0"
#25
b10 !
b10 $
1"
#30
0"
#35
b11 !
b11 $
1"
#40
0"
#45
b100 !
b100 $
1"
#50
0"
#55
b101 !
b101 $
1"
#60
0"
#65
b110 !
b110 $
1"
#70
0"
#75
b111 !
b111 $
1"
#80
0"
#85
b1000 !
b1000 $
1"
#90
0"
#95
b1001 !
b1001 $
1"
#100
0"
#105
b1010 !
b1010 $
1"
#110
0"
1#
#115
b0 !
b0 $
1"
#120
0"
0#
#125
b1 !
b1 $
1"
#130
0"
#135
b10 !
b10 $
1"
#140
0"
#145
b11 !
b11 $
1"
#150
0"
#155
b100 !
b100 $
1"
#160
0"
#165
b101 !
b101 $
1"
