Day_4/2to4decoder.v
module decoder2to4(input [1:0]a,input en, output reg [3:0]y);
always@(*) begin
if (en==0)
 y=4'b000;
else 
case(a)
2'b00:y= 4'b0001;
2'b01:y= 4'b0010;
2'b01:y= 4'b0100;
2'b11:y= 4'b1000;
default:y=4'b0000;
endcase
end 
endmodule

Day_4/2to4decoder_tb.v
module decoder_2x4_tb;
reg en;
reg [1:0]a;
wire [3:0]y;

decoder2to4 dut(a,en,y);

initial begin

$monitor("en=%b a=%b | y=%b",en,a,y);
$dumpfile("decoder.vcd");
$dumpvars();

en=0;a=2'b00;#10
en=0;a=2'b01;#10
en=0;a=2'b10;#10
en=0;a=2'b11;#10


en=1;a=2'b00;#10
en=1;a=2'b01;#10
en=1;a=2'b10;#10
en=1;a=2'b11;#10
$finish;

end
endmodule

Day_4/decoder.vcd
$date
	Fri Sep 19 14:15:46 2025
$end
$version
	Icarus Verilog
$end
$timescale
	1s
$end
$scope module decoder_2x4_tb $end
$var wire 4 ! y [3:0] $end
$var reg 2 " a [1:0] $end
$var reg 1 # en $end
$scope module dut $end
$var wire 2 $ a [1:0] $end
$var wire 1 # en $end
$var reg 4 % y [3:0] $end
$upscope $end
$upscope $end
$enddefinitions $end
$comment Show the parameter values. $end
$dumpall
$end
#0
$dumpvars
b0 %
b0 $
0#
b0 "
b0 !
$end
#10
b1 "
b1 $
#20
b10 "
b10 $
#30
b11 "
b11 $
#40
b1 !
b1 %
b0 "
b0 $
1#
#50
b10 !
b10 %
b1 "
b1 $
#60
b0 !
b0 %
b10 "
b10 $
#70
b1000 !
b1000 %
b11 "
b11 $
