Day_4/FA.v
module full_adder(input a,b,c,output reg sum,carry);
always @(*) begin
sum=a^b^c;
carry=(a&b)|(b&c)|(a&c);
end
endmodule

Day_4/FA_tb.v
module tb_full_adder;
reg a,b,c;
wire sum,carry;

full_adder uut(.a(a),.b(b),.c(c),.sum(sum),.carry(carry));

initial begin
a=0;b=0;c=0;
#10 a=0;b=0;c=1;
#10 a=0;b=1;c=0;
#10 a=0;b=1;c=1;
#10 a=1;b=0;c=0;
#10 a=1;b=0;c=1;
#10 a=1;b=1;c=0;
#10 a=1;b=1;c=1;
#10 $finish;
end

initial begin

$monitor("time=%0t a=%b b=%b c=%b | sum=%b carry=%b",$time,a,b,c,sum,carry);
$dumpfile ("raj.vcd");
$dumpvars;
end
endmodule

Day_4/raj.vcd
$date
	Thu Sep 18 16:26:07 2025
$end
$version
	Icarus Verilog
$end
$timescale
	1s
$end
$scope module tb_full_adder $end
$var wire 1 ! sum $end
$var wire 1 " carry $end
$var reg 1 # a $end
$var reg 1 $ b $end
$var reg 1 % c $end
$scope module uut $end
$var wire 1 # a $end
$var wire 1 $ b $end
$var wire 1 % c $end
$var reg 1 " carry $end
$var reg 1 ! sum $end
$upscope $end
$upscope $end
$enddefinitions $end
$comment Show the parameter values. $end
$dumpall
$end
#0
$dumpvars
0%
0$
0#
0"
0!
$end
#10
1!
1%
#20
0%
1$
#30
1"
0!
1%
#40
0"
1!
0%
0$
1#
#50
1"
0!
1%
#60
0%
1$
#70
1!
1%
